distproc/__init__.py
distproc/asmparse.py
distproc/assembler.py
distproc/command_gen.py
distproc/compiler.py
distproc/executable.py
distproc/hwconfig.py
distproc/ir/__init__.py
distproc/ir/instructions.py
distproc/ir/ir.py
distproc/ir/passes.py
distproc/openqasm/__init__.py
distproc/openqasm/gate_map.py
distproc/openqasm/qubit_map.py
distproc/openqasm/visitor.py
distproc-25.8.0.dist-info/METADATA
distproc-25.8.0.dist-info/WHEEL
distproc-25.8.0.dist-info/RECORD
