Metadata-Version: 2.4
Name: distproc
Version: 25.8.0
Requires-Python: >=3.10
Requires-Dist: attrs>=25
Requires-Dist: networkx~=3.4
Requires-Dist: numpy~=2.2
Requires-Dist: pandas>=2.1
Requires-Dist: parse>=1.20
Requires-Dist: pytest
Provides-Extra: openqasm3
Requires-Dist: openpulse; extra == 'openqasm3'
Requires-Dist: openqasm3; extra == 'openqasm3'
Provides-Extra: openqasm3-test
Requires-Dist: openpulse; extra == 'openqasm3-test'
Requires-Dist: oqpy; extra == 'openqasm3-test'
Requires-Dist: qiskit; extra == 'openqasm3-test'
